{
    "id": 60,
    "nombre": "AgregarInformacionAdicional",
    "descripcion": "Método para agregar la información adicional de un cliente.",
    "entrada": {
        "clienteUId": {
            "type": "number",
            "description": "Identificador único de cliente."
        },
        "sdtInformacionAdicional": {
            "type": "object",
            "description": "Listado de datos adicionales.",
            "properties": {
                "clave": {
                    "type": "string",
                    "description": "Identificador de información adicional."
                },
                "valor": {
                    "type": "string",
                    "description": "Valor de información adicional."
                }
            }
        },
        "modo": {
            "type": "string",
            "description": "[Hidden, valor fijo 'INS' para este método]."
        }
    },
    "salida": {},
    "sistema": "Clientes"
}