{
    "id": 259,
    "nombre": "ActualizarIntegranteGrupo",
    "descripcion": "Método para actualizar un integrante de un grupo de crédito.",
    "entrada": {
        "grupoId": {
            "type": "integer",
            "description": "Identificador de grupo."
        },
        "sdtIntegranteGrupo": {
            "type": "object",
            "description": "Datos del integrante.",
            "properties": {
                "clienteUId": {
                    "type": "number",
                    "description": "Identificador único del cliente."
                },
                "cuenta": {
                    "type": "string",
                    "description": "Nombre de la cuenta."
                },
                "tipoIntegranteId": {
                    "type": "integer",
                    "description": "Tipo de integrante a ser actualizado."
                },
                "tipoIntegrante": {
                    "type": "string",
                    "description": "Descripción del tipo de integrante."
                },
                "fechaAlta": {
                    "type": "string",
                    "description": "Fecha de alta del integrante."
                },
                "fechaBaja": {
                    "type": "string",
                    "description": "Fecha de baja del integrante."
                },
                "identificacionAlternativa": {
                    "type": "string",
                    "description": "Identificación alternativa del integrante."
                }
            },
            "required": [
                "clienteUId"
            ]
        }
    },
    "salida": {},
    "sistema": "Microfinanzas"
}