{
    "nombre": "ObtenerClientedeunaOperacion",
    "descripcion": "Método para obtener el cliente asociado a una operación. \n",
    "entrada": "### Datos de entrada \n\nNombre | Tipo | Comentarios \n--------- | ----------- | ----------- \noperacionUId | Long | Identificador único de la operación \n\n",
    "salida": "### Datos de salida \n\nNombre | Tipo | Comentarios \n--------- | ----------- | ----------- \nclienteUId | Long | Identificador único de cliente. \n\n\n",
    "intro": "# Obtener Cliente de una Operación \n\nMétodo para obtener el cliente asociado a una operación. \n\nNombre publicación | Programa | Global/País \n--------- | ----------- | ----------- \nBTContabilidad.ObtenerClienteDeOperacion | RBTPG298 | Global \n\n",
    "error": "### Errores \n\nCódigo | Descripción \n--------- | ----------- \n30001 | No se recibió identificador único de operación. \n30101 | No se recupero la operación para el identificador recibido. \n\n \n",
    "sistema": "Contabilidad",
    "ej_in": "> Ejemplo de invocación al método Obtener Cliente de una Operación: \n\n<code-group> \n<code-block title=\"XML\" active> \n```xml \n<soapenv:Envelope xmlns:soapenv=\"http://schemas.xmlsoap.org/soap/envelope/\" xmlns:bts=\"http://uy.com.dlya.bantotal/BTSOA/\"> \n   <soapenv:Header/> \n   <soapenv:Body> \n      <bts:BTContabilidad.ObtenerClienteDeOperacion> \n         <bts:Btinreq> \n            <bts:Canal>BTDIGITAL</bts:Canal> \n            <bts:Requerimiento>1</bts:Requerimiento> \n            <bts:Usuario>BANTOTAL</bts:Usuario> \n            <bts:Token>0d3a8212b3F955E77534D3E0</bts:Token> \n            <bts:Device>AC</bts:Device> \n         </bts:Btinreq> \n         <bts:operacionUId>787</bts:operacionUId> \n      </bts:BTContabilidad.ObtenerClienteDeOperacion> \n   </soapenv:Body> \n</soapenv:Envelope> \n``` \n</code-block> \n\n<code-block title=\"JSON\"> \n```json \ncurl -X POST \\ \n  'http://btd-bantotal.eastus2.cloudapp.azure.com:4462/btdeveloper/servlet/com.dlya.bantotal.odwsbt_BTContabilidad_v1?ObtenerClienteDeOperacion' \\ \n  -H 'cache-control: no-cache' \\ \n  -H 'content-type: application/json' \\ \n  -H 'postman-token: 6b958b92-122d-189b-a0b5-7a4a0569b79d' \\ \n  -d '{ \n\t\"bts:Btinreq\": { \n\t  \"bts:Canal\": \"BTDIGITAL\", \n\t  \"bts:Requerimiento\": \"1\", \n\t  \"bts:Usuario\": \"BANTOTAL\", \n\t  \"bts:Token\": \"0d3a8212b3F955E77534D3E0\", \n\t  \"bts:Device\": \"AC\" \n\t}, \n\t\"bts:operacionUId\": \"787\" \n} \n``` \n</code-block> \n</code-group> \n\n",
    "ej_out": "> El POST retornará la siguiente estructura: \n\n<code-group> \n<code-block title=\"XML\" active> \n```xml \n<SOAP-ENV:Envelope xmlns:SOAP-ENV=\"http://schemas.xmlsoap.org/soap/envelope/\" xmlns:xsd=\"http://www.w3.org/2001/XMLSchema\" xmlns:SOAP-ENC=\"http://schemas.xmlsoap.org/soap/encoding/\" xmlns:xsi=\"http://www.w3.org/2001/XMLSchema-instance\"> \n   <SOAP-ENV:Body> \n      <BTContabilidad.ObtenerClienteDeOperacionResponse xmlns=\"http://uy.com.dlya.bantotal/BTSOA/\"> \n         <Btinreq> \n            <Device>AC</Device> \n            <Usuario>BANTOTAL</Usuario> \n            <Requerimiento>1</Requerimiento> \n            <Canal>BTDIGITAL</Canal> \n            <Token>0d3a8212b3F955E77534D3E0</Token> \n         </Btinreq> \n         <clienteUId>822</clienteUId> \n         <Erroresnegocio></Erroresnegocio> \n         <Btoutreq> \n            <Numero>110086</Numero> \n            <Estado>OK</Estado> \n            <Servicio>BTContabilidad.ObtenerClienteDeOperacion</Servicio> \n            <Requerimiento>1</Requerimiento> \n            <Fecha>2021-02-18</Fecha> \n            <Canal>BTDIGITAL</Canal> \n            <Hora>14:37:54</Hora> \n         </Btoutreq> \n      </BTContabilidad.ObtenerClienteDeOperacionResponse> \n   </SOAP-ENV:Body> \n</SOAP-ENV:Envelope> \n``` \n</code-block> \n\n<code-block title=\"JSON\"> \n```json \n { \n \t\"Btinreq\": { \n\t  \"Device\": \"AC\", \n\t  \"Usuario\": \"BANTOTAL\", \n\t  \"Requerimiento\": \"1\", \n\t  \"Canal\": \"BTDIGITAL\", \n\t  \"Token\": \"0d3a8212b3F955E77534D3E0\" \n\t}, \n\t\"clienteUId\": \"822\", \n\t\"Btoutreq\": { \n\t  \"Numero\": \"110086\", \n\t  \"Estado\": \"OK\", \n\t  \"Servicio\": \"BTContabilidad.ObtenerClienteDeOperacion\", \n\t  \"Requerimiento\": \"1\", \n\t  \"Fecha\": \"2021-02-18\", \n\t  \"Canal\": \"BTDIGITAL\", \n\t  \"Hora\": \"14:37:54\" \n\t} \n } \n``` \n</code-block> \n</code-group> \n\n",
    "AzureSearch_DocumentKey": 153
}