{
    "nombre": "ContratarProductoconAltadeFacultades",
    "descripcion": "Método para contratar una cuenta corriente en Bantotal, dando de alta las facultades. \n",
    "entrada": "### Datos de entrada \n\nNombre | Tipo | Comentarios \n--------- | ----------- | ----------- \nclienteUId | Long | Identificador único de cliente \nproductoUId | Long | Identificador único de producto \nnombreSubCuenta | String | Nombre de la cuenta cliente \ntipoIntegracion | String | Tipo de integración (B-Indistinta/C-Conjunta) \n\n",
    "salida": "### Datos de salida \n\nNombre | Tipo | Comentarios \n--------- | ----------- | ----------- \noperacionUId | Long | Identificador único de operación \n\n",
    "intro": "# Contratar Producto con Alta de Facultades \n\nMétodo para contratar una cuenta corriente en Bantotal, dando de alta las facultades. \n\nNombre publicación | Programa | Global/País \n--------- | ----------- | ----------- \nBTCuentasDeAhorro.ContratarConFacultades | RBTPG100 | Global \n\n",
    "error": "### Errores \n\nCódigo | Descripción \n--------- | ----------- \n30001 | No se recibió el identificador de cliente \n30002 | No se recuperó la cuenta para el Identificador \n\n \n",
    "sistema": "CuentasdeAhorro",
    "ej_in": "> Ejemplo de invocación al método Contratar Producto con Alta de facultades: \n\n<code-group> \n<code-block title=\"XML\" active> \n```xml \n<soapenv:Envelope xmlns:soapenv=\"http://schemas.xmlsoap.org/soap/envelope/\" xmlns:bts=\"http://uy.com.dlya.bantotal/BTSOA/\"> \n   <soapenv:Header/> \n   <soapenv:Body> \n      <bts:BTCuentasDeAhorro.ContratarConFacultades> \n         <bts:Btinreq> \n            <bts:Device>AV</bts:Device> \n            <bts:Usuario>MINSTALADOR</bts:Usuario> \n            <bts:Requerimiento></bts:Requerimiento> \n            <bts:Canal>BTDIGITAL</bts:Canal> \n            <bts:Token>268b6d23eb4A8B5C60A82434</bts:Token> \n         </bts:Btinreq> \n         <bts:clienteUId>4</bts:clienteUId> \n         <bts:productoUId>1</bts:productoUId> \n         <bts:nombreSubCuenta>C.A. Ahorro</bts:nombreSubCuenta> \n         <bts:tipoIntegracion>B</bts:tipoIntegracion> \n      </bts:BTCuentasDeAhorro.ContratarConFacultades> \n   </soapenv:Body> \n</soapenv:Envelope> \n``` \n</code-block> \n\n<code-block title=\"JSON\"> \n```json \ncurl -X POST \\ \n  'http://btd-bantotal.eastus2.cloudapp.azure.com:4462/btdeveloper/servlet/com.dlya.bantotal.odwsbt_BTCuentasDeAhorro?ContratarConFacultades=' \\ \n  -H 'cache-control: no-cache' \\ \n  -H 'content-type: application/json' \\ \n  -H 'postman-token: b80d8c23-883d-589a-228b-4009ae6eba1c' \\ \n  -d '{ \n\t\"Btinreq\": { \n\t\t\"Device\": \"AV\", \n\t\t\"Usuario\": \"MINSTALADOR\", \n\t\t\"Requerimiento\": \"\", \n\t\t\"Canal\": \"BTDIGITAL\", \n\t\t\"Token\": \"fa2c02c95a4A8B5C60A82434\" \n\t}, \n    \"clienteUId\": 4, \n    \"productoUId\": 1, \n    \"nombreSubCuenta\": \"C.A. Pesos\", \n    \"tipoIntegracion\": \"B\" \n}' \n``` \n</code-block> \n</code-group> \n\n",
    "ej_out": "> El POST retornará la siguiente estructura: \n\n<code-group> \n<code-block title=\"XML\" active> \n```xml \n<SOAP-ENV:Envelope xmlns:SOAP-ENV=\"http://schemas.xmlsoap.org/soap/envelope/\" xmlns:xsd=\"http://www.w3.org/2001/XMLSchema\" xmlns:SOAP-ENC=\"http://schemas.xmlsoap.org/soap/encoding/\" xmlns:xsi=\"http://www.w3.org/2001/XMLSchema-instance\"> \n   <SOAP-ENV:Body> \n      <BTCuentasDeAhorro.ContratarConFacultadesResponse xmlns=\"http://uy.com.dlya.bantotal/BTSOA/\"> \n         <Btinreq> \n            <Device>AV</Device> \n            <Usuario>MINSTALADOR</Usuario> \n            <Requerimiento/> \n            <Canal>BTDIGITAL</Canal> \n            <Token>268b6d23eb4A8B5C60A82434</Token> \n         </Btinreq> \n         <operacionUId>401</operacionUId> \n         <Erroresnegocio></Erroresnegocio> \n         <Btoutreq> \n            <Numero>853</Numero> \n            <Estado>OK</Estado> \n            <Servicio>BTCuentasDeAhorro.ContratarConFacultades</Servicio> \n            <Fecha>2017-12-18</Fecha> \n            <Requerimiento/> \n            <Hora>10:33:16</Hora> \n            <Canal>BTDIGITAL</Canal> \n         </Btoutreq> \n      </BTCuentasDeAhorro.ContratarConFacultadesResponse> \n   </SOAP-ENV:Body> \n</SOAP-ENV:Envelope> \n``` \n</code-block> \n\n<code-block title=\"JSON\"> \n```json \n'{ \n\t\"Btinreq\": { \n\t\t\"Device\": \"AV\", \n\t\t\"Usuario\": \"MINSTALADOR\", \n\t\t\"Requerimiento\": \"\", \n\t\t\"Canal\": \"BTDIGITAL\", \n\t\t\"Token\": \"fa2c02c95a4A8B5C60A82434\" \n\t}, \n    \"operacionUId\": \"402\", \n    \"Erroresnegocio\": { \n        \"BTErrorNegocio\": [] \n    }, \n    \"Btoutreq\": { \n        \"Numero\": \"855\", \n        \"Estado\": \"OK\", \n        \"Servicio\": \"BTCuentasDeAhorro.ContratarConFacultades\", \n        \"Fecha\": \"2017-12-18\", \n        \"Requerimiento\": \"\", \n        \"Hora\": \"10:35:49\", \n        \"Canal\": \"BTDIGITAL\" \n    } \n}' \n``` \n</code-block> \n</code-group> \n\n",
    "AzureSearch_DocumentKey": 196
}