{
    "nombre": "Cancelar",
    "descripcion": "Método para realizar la liquidación de una cuenta vista. \n",
    "entrada": "### Datos de entrada \n\nNombre | Tipo | Comentarios \n--------- | ----------- | ----------- \nclienteUId | Long | Identificador único de cuenta cliente. \ncuentaLiquidacionUId | Long | Identificador único de la cuenta vista a cancelar. \ncuentaAcreditacionUId | Long | Identificador único de la cuenta vista de acreditación/cobro de la liquidación. \n\n",
    "salida": "### Datos de salida \n\nNombre | Tipo | Comentarios \n--------- | ----------- | ----------- \nmovimientoUId | Long | Identificador único del movimiento realizado. \n\n",
    "intro": "# Cancelar \n\nMétodo para realizar la liquidación de una cuenta vista. \n\nNombre publicación | Programa | Global/País \n--------- | ----------- | ----------- \nBTCuentasVista.Cancelar | RBTPG474 | Global \n\n",
    "error": "### Errores \n\nCódigo | Descripción \n--------- | ----------- \n30001 | No se recibió el identificador del cliente. \n30002 | La cuenta indicada no existe. \n30003 | No se recibió el identificador de la cuenta. \n30004 | La cuenta indicada no existe. \n30005 | La cuenta a liquidar y la cuenta de acreditación no pueden ser la misma. \n30007 | La cuenta indicada no pertenece al cliente. \n30006 | La cuenta de cobro indicada no existe. \n30008 | Las monedas de la cuenta a liquidar y la cuenta de acreditación deben ser la misma. \n30009 | No se pudo obtener el identificador para el movimiento realizado. \n30100 | Error en la contabilización. \n40001 | Operativa fuera de horario \n40003 | Producto cancelado. \n40004 | No se definió transacción a ejecutar. \n40006 | La Operación tiene Bloqueos; no puede ser liquidada. \n40007 | El producto se encuentra sobregirado, no es posible realizar la liquidación. \n40008 | La cuenta tiene Tarjeta de débito asociada; no puede ser liquidada. \n40009 | El producto paga la comisión del paquete, debe modificarse la instrucción. \n40010 | NO SE DEFINIO LA CARPETA EN LA QUE SE GUARDARÁ EL ARCHIVO. \n40013 | Usuario no autorizado a consultar esta Cuenta. \n40014 | Usuario no autorizado a consultar esta Cuenta. \n40015 | No es posible realizar la liquidación. \n40016 | El titular de la cuenta no es una persona física. \n40017 | No es posible operar con una cuenta conjunta. \n40018 | La operación no permite operar. \n40019 | La operación de acreditación no permite operar. \n40020 | No se indicó cuenta de cobro/acreditación. \n40021 | La operación a liquidar no puede ser CTS. \n\n \n",
    "sistema": "CuentasVista",
    "ej_in": "> Ejemplo de invocación al método Cancelar: \n\n<code-group> \n<code-block title=\"XML\" active> \n```xml \n<soapenv:Envelope xmlns:soapenv=\"http://schemas.xmlsoap.org/soap/envelope/\" xmlns:bts=\"http://uy.com.dlya.bantotal/BTSOA/\"> \n   <soapenv:Header/> \n   <soapenv:Body> \n      <bts:BTCuentasVista.Cancelar> \n         <bts:Btinreq> \n            <bts:Usuario>INSTALADOR</bts:Usuario> \n            <bts:Canal>BTDIGITAL</bts:Canal> \n            <bts:Device>GP</bts:Device> \n            <bts:Token>65386256C895CD01D7DC796E</bts:Token> \n            <bts:Requerimiento>1</bts:Requerimiento> \n         </bts:Btinreq> \n         <bts:clienteUId>201</bts:clienteUId> \n         <bts:cuentaLiquidacionUId>310</bts:cuentaLiquidacionUId> \n         <bts:cuentaAcreditacionUId>311</bts:cuentaAcreditacionUId> \n      </bts:BTCuentasVista.Cancelar> \n   </soapenv:Body> \n</soapenv:Envelope> \n``` \n</code-block> \n\n<code-block title=\"JSON\"> \n```json \ncurl -X POST \\   \n  'http://btd-bantotal.eastus2.cloudapp.azure.com:4462/btdeveloper/servlet/com.dlya.bantotal.odwsbt_BTCuentasVista?Cancelar' \\ \n  -H 'cache-control: no-cache' \\ \n  -H 'content-type: application/json' \\ \n  -H 'postman-token: 52baf1dc-e302-90a6-0de1-24fa234c0379' \\ \n  -d '{ \n\t\"Btinreq\": { \n\t\t\"Device\": \"AV\", \n\t\t\"Usuario\": \"MINSTALADOR\", \n\t\t\"Requerimiento\": \"\", \n\t\t\"Canal\": \"BTDIGITAL\", \n\t\t\"Token\": \"fa2c02c95a4A8B5C60A82434\" \n\t}, \n\t\"clienteUId\": \"201\", \n\t\"cuentaLiquidacionUId\": \"310\", \n\t\"cuentaAcreditacionUId\": \"311\", \n}' \n``` \n</code-block> \n</code-group> \n\n",
    "ej_out": "> El POST retornará la siguiente estructura: \n\n<code-group> \n<code-block title=\"XML\" active> \n```xml \n<SOAP-ENV:Envelope xmlns:SOAP-ENV=\"http://schemas.xmlsoap.org/soap/envelope/\" xmlns:xsd=\"http://www.w3.org/2001/XMLSchema\" xmlns:SOAP-ENC=\"http://schemas.xmlsoap.org/soap/encoding/\" xmlns:xsi=\"http://www.w3.org/2001/XMLSchema-instance\"> \n   <SOAP-ENV:Body> \n      <BTCuentasVista.CancelarResponse xmlns=\"http://uy.com.dlya.bantotal/BTSOA/\"> \n         <Btinreq> \n            <Device>GP</Device> \n            <Usuario>INSTALADOR</Usuario> \n            <Requerimiento>1</Requerimiento> \n            <Canal>BTDIGITAL</Canal> \n            <Token>65386256C895CD01D7DC796E</Token> \n         </Btinreq> \n         <movimientoUId>1032</movimientoUId> \n         <Erroresnegocio></Erroresnegocio> \n         <Btoutreq> \n            <Numero>12044</Numero> \n            <Estado>OK</Estado> \n            <Servicio>BTCuentasVista.Cancelar</Servicio> \n            <Requerimiento>1</Requerimiento> \n            <Fecha>2023-05-23</Fecha> \n            <Canal>BTDIGITAL</Canal> \n            <Hora>15:19:22</Hora> \n         </Btoutreq> \n      </BTCuentasVista.CancelarResponse> \n   </SOAP-ENV:Body> \n</SOAP-ENV:Envelope> \n``` \n</code-block> \n\n<code-block title=\"JSON\"> \n```json \n'{ \n\t\"Btinreq\": { \n\t\t\"Device\": \"AV\", \n\t\t\"Usuario\": \"MINSTALADOR\", \n\t\t\"Requerimiento\": \"\", \n\t\t\"Canal\": \"BTDIGITAL\", \n\t\t\"Token\": \"fa2c02c95a4A8B5C60A82434\" \n\t}, \n    \"movimientoUId\": 1032, \n    \"Btoutreq\": { \n        \"Numero\": 823, \n        \"Estado\": \"OK\", \n        \"Servicio\": \"BTCuentasVista.Cancelar\", \n        \"Requerimiento\": \"1\", \n        \"Fecha\": \"2018-11-12\", \n        \"Hora\": \"17:47:27\", \n        \"Canal\": \"BTDIGITAL\" \n    } \n}' \n``` \n</code-block> \n</code-group> \n\n",
    "AzureSearch_DocumentKey": 208
}