{
    "nombre": "AgregarInformacionAdicional",
    "descripcion": "Método para agregar la información adicional de una persona. \n",
    "entrada": "### Datos de entrada \n\nNombre | Tipo | Comentarios \n--------- | ----------- | ----------- \npersonaUId | Long | Identificador único de persona. \nsdtInformacionAdicional | sBTDatoLista | Listado de datos. \n\nLos campos del tipo de dato estructurado sBTDatoLista son los siguientes: \n\nCampo | Tipo | Comentarios \n--------- | ----------- | ----------- \nclave | String | Identificador de información adicional. \nvalor | String | Valor de información adicional. \n\n\n",
    "salida": "### Datos de salida \n\nNo aplica. \n\n\n",
    "intro": "# Agregar Información Adicional \n\nMétodo para agregar la información adicional de una persona. \n\nNombre publicación | Programa | Global/País \n--------- | ----------- | ----------- \nBTPersonas.AgregarInformacionAdicional | RBTPG517 | Global \n\n",
    "error": "### Errores \n\nCódigo | Descripción \n----------- | ----------- \n30001 | No se recibió el identificador de persona. \n\n\n \n",
    "sistema": "Personas",
    "ej_in": "> Ejemplo de invocación al servicio de Agregar Información Adicional: \n\n<code-group> \n<code-block title=\"XML\" active> \n```xml \n<soapenv:Envelope xmlns:soapenv=\"http://schemas.xmlsoap.org/soap/envelope/\" xmlns:bts=\"http://uy.com.dlya.bantotal/BTSOA/\"> \n   <soapenv:Header/> \n   <soapenv:Body> \n      <bts:BTPersonas.AgregarInformacionAdicional> \n         <bts:Btinreq> \n            <bts:Device>1</bts:Device> \n            <bts:Usuario>MINSTALADOR</bts:Usuario> \n            <bts:Token>976EB9CBE6D99B71A5E627F1</bts:Token> \n            <bts:Canal>BTDIGITAL</bts:Canal> \n            <bts:Requerimiento>1</bts:Requerimiento> \n         </bts:Btinreq> \n         <bts:personaUId>204</bts:personaUId> \n         <bts:sdtInformacionAdicional> \n            <bts:sBTDatoLista> \n               <bts:Clave>Código TIN</bts:Clave> \n               <bts:Valor>1256</bts:Valor> \n            </bts:sBTDatoLista> \n         </bts:sdtInformacionAdicional> \n      </bts:BTPersonas.AgregarInformacionAdicional> \n   </soapenv:Body> \n</soapenv:Envelope> \n``` \n</code-block> \n\n<code-block title=\"JSON\"> \n```json \ncurl -X POST \\ \n\t'http://btd-bantotal.eastus2.cloudapp.azure.com:4462/btdeveloper/servlet/com.dlya.bantotal.odwsbt_BTPersonas?AgregarInformacionAdicional' \\ \n\t-H 'cache-control: no-cache' \\ \n\t-H 'content-type: application/json' \\ \n\t-H 'postman-token: 52baf1dc-e302-90a6-0de1-24fa234c0379' \\ \n\t-d '{ \n\t\"Btinreq\": { \n\t  \"Device\": \"1\", \n\t  \"Usuario\": \"MINSTALADOR\", \n\t  \"Token\": \"9CBE6DC33CD93505A5382434\", \n\t  \"Canal\": \"BTDIGITAL\", \n\t  \"Requerimiento\": \"1\" \n\t}, \n\t\"personaUId\": 204, \n        \"sdtInformacionAdicional\": { \n          \"sBTDatoLista\": { \n            \"Clave\": \"Código TIN\", \n            \"Valor\": 1256 \n          } \n        } \n}' \n``` \n</code-block> \n</code-group> \n\n",
    "ej_out": "> El POST retornará la siguiente estructura: \n\n<code-group> \n<code-block title=\"XML\" active> \n```xml \n<SOAP-ENV:Envelope xmlns:SOAP-ENV=\"http://schemas.xmlsoap.org/soap/envelope/\" xmlns:xsd=\"http://www.w3.org/2001/XMLSchema\" xmlns:SOAP-ENC=\"http://schemas.xmlsoap.org/soap/encoding/\" xmlns:xsi=\"http://www.w3.org/2001/XMLSchema-instance\"> \n   <SOAP-ENV:Body> \n      <BTPersonas.AgregarInformacionAdicionalResponse xmlns=\"http://uy.com.dlya.bantotal/BTSOA/\"> \n         <Btinreq> \n            <Device>1</Device> \n            <Usuario>MINSTALADOR</Usuario> \n            <Requerimiento>1</Requerimiento> \n            <Canal>BTDIGITAL</Canal> \n            <Token>976EB9CBE6D99B71A5E627F1</Token> \n         </Btinreq> \n         <Erroresnegocio></Erroresnegocio> \n         <Btoutreq> \n            <Numero>10762</Numero> \n            <Servicio>BTPersonas.AgregarInformacionAdicional</Servicio> \n            <Estado>OK</Estado> \n            <Requerimiento>1</Requerimiento> \n            <Fecha>2023-05-10</Fecha> \n            <Hora>12:46:32</Hora> \n            <Canal>BTDIGITAL</Canal> \n         </Btoutreq> \n      </BTPersonas.AgregarInformacionAdicionalResponse> \n   </SOAP-ENV:Body> \n</SOAP-ENV:Envelope> \n``` \n</code-block> \n\n<code-block title=\"JSON\"> \n```json \n{ \n   \"Btinreq\": { \n      \"Device\": \"1\", \n      \"Usuario\": \"MINSTALADOR\", \n      \"Token\": \"16c1cFC33CD93505A5382434\", \n      \"Canal\": \"BTDIGITAL\", \n      \"Requerimiento\": \"1\" \n   }, \n\n   \"Btoutreq\": { \n      \"Numero\": \"111399\", \n      \"Estado\": \"OK\", \n      \"Servicio\": \"BTPersonas.AgregarInformacionAdicional\", \n      \"Requerimiento\": \"1\", \n      \"Fecha\": \"2023-05-10\", \n      \"Canal\": \"BTDIGITAL\", \n      \"Hora\": \"14:28:56\" \n   } \n}' \n``` \n</code-block> \n</code-group> \n\n",
    "AzureSearch_DocumentKey": 336
}