{
    "nombre": "EvaluarRegladeNegocio",
    "descripcion": "Método para evaluar una determinada regla de negocio. \n",
    "entrada": "### Datos de entrada \n\nNombre | Tipo | Comentarios \n--------- | ----------- | ----------- \nreglaId | Long | Código de regla de negocio. \nsdtVariables | sBTVariable | Listado de variables. \n\nLos campos del tipo de dato estructurado sBTVariableRegla son los siguientes: \n\nNombre | Tipo | Comentarios \n--------- | ----------- | ----------- \nnombre | String | Nombre de variable. \nvalor | String | Valor de variable.  \n\n",
    "salida": "### Datos de salida \n\nNombre | Tipo | Comentarios \n--------- | ----------- | ----------- \nresultado | String | Resultado de la evaluación.  \nretorno | String | Retorno de la evaluación.  \n\n",
    "intro": "# Evaluar Regla de Negocio \n\nMétodo para evaluar una determinada regla de negocio. \n\nNombre publicación | Programa | Global/País \n--------- | ----------- | ----------- \nBTReglasNegocio.EvaluarReglaNegocio | RBTPGR55 | Global \n\n",
    "error": "### Errores \n\nCódigo | Descripción \n--------- | ----------- \n1011050 | No se recibio ID de Regla. \n40001 | Error de Parametrización. \n\n \n",
    "sistema": "ReglasdeNegocio",
    "ej_in": "> Ejemplo de invocación al servicio de Evaluar Regla de Negocio: \n\n<code-group> \n<code-block title=\"XML\" active> \n```xml \n<soapenv:Envelope xmlns:soapenv=\"http://schemas.xmlsoap.org/soap/envelope/\" xmlns:bts=\"http://uy.com.dlya.bantotal/BTSOA/\"> \n   <soapenv:Header/> \n   <soapenv:Body> \n      <bts:BTReglasNegocio.EvaluarReglaNegocio> \n         <bts:Btinreq> \n            <bts:Device>GP</bts:Device> \n            <bts:Usuario>INSTALADOR</bts:Usuario> \n            <bts:Requerimiento>1</bts:Requerimiento> \n            <bts:Canal>BTDIGITAL</bts:Canal> \n            <bts:Token>86b12d9cbaCD285A89A23FBE</bts:Token> \n         </bts:Btinreq> \n         <bts:reglaId>4</bts:reglaId> \n         <bts:sdtVariables> \n            <bts:SdtsBTVariable> \n               <bts:valor>S</bts:valor> \n               <bts:nombre>CHECKAUX2</bts:nombre> \n            </bts:SdtsBTVariable> \n         </bts:sdtVariables> \n      </bts:BTReglasNegocio.EvaluarReglaNegocio> \n   </soapenv:Body> \n</soapenv:Envelope> \n``` \n</code-block> \n\n<code-block title=\"JSON\"> \n```json \ncurl -X POST \\ \n    'http://btd-bantotal.eastus2.cloudapp.azure.com:4462/btdeveloper/servlet/com.dlya.bantotal.odwsbt_BTReglasNegocio?EvaluarReglaNegocio' \\ \n    -H 'cache-control: no-cache' \\ \n    -H 'content-type: application/json' \\ \n    -H 'postman-token: 52baf1dc-e302-90a6-0de1-24fa234c0379' \\ \n    -d '{ \n    \"Btinreq\": { \n        \"Device\": \"GP\", \n        \"Usuario\": \"MINSTALADOR\", \n        \"Requerimiento\": \"1\", \n        \"Canal\": \"BTDIGITAL\", \n        \"Token\": \"bc8b678bc44A8B5C60A82434\" \n    }, \n    \"reglaId\": \"4\", \n    \"sdtVariables\": { \n        \"SdtsBTVariable\": { \n            \"valor\": \"S\", \n            \"nombre\": \"CHECKAUX2\" \n        }, \n    }, \n}' \n``` \n</code-block> \n</code-group> \n\n",
    "ej_out": "> El POST retornará la siguiente estructura: \n\n<code-group> \n<code-block title=\"XML\" active> \n```xml \n<SOAP-ENV:Envelope xmlns:SOAP-ENV=\"http://schemas.xmlsoap.org/soap/envelope/\" xmlns:xsd=\"http://www.w3.org/2001/XMLSchema\" xmlns:SOAP-ENC=\"http://schemas.xmlsoap.org/soap/encoding/\" xmlns:xsi=\"http://www.w3.org/2001/XMLSchema-instance\"> \n   <SOAP-ENV:Body> \n      <BTReglasNegocio.EvaluarReglaNegocioResponse xmlns=\"http://uy.com.dlya.bantotal/BTSOA/\"> \n         <Btinreq> \n            <Device>GP</Device> \n            <Usuario>INSTALADOR</Usuario> \n            <Requerimiento>1</Requerimiento> \n            <Canal>BTDIGITAL</Canal> \n            <Token>86b12d9cbaCD285A89A23FBE</Token> \n         </Btinreq> \n         <resultado>VERDADERO</resultado> \n         <retorno>3</retorno> \n         <Erroresnegocio></Erroresnegocio> \n         <Btoutreq> \n            <Numero>44659</Numero> \n            <Estado>OK</Estado> \n            <Servicio>BTReglasNegocio.EvaluarReglaNegocio</Servicio> \n            <Fecha>2022-06-02</Fecha> \n            <Requerimiento>1</Requerimiento> \n            <Hora>10:27:36</Hora> \n            <Canal>BTDIGITAL</Canal> \n         </Btoutreq> \n      </BTReglasNegocio.EvaluarReglaNegocioResponse> \n   </SOAP-ENV:Body> \n</SOAP-ENV:Envelope> \n``` \n</code-block> \n\n<code-block title=\"JSON\"> \n```json \n{ \n    \"Btinreq\": { \n        \"Device\": \"GP\", \n        \"Usuario\": \"MINSTALADOR\", \n        \"Requerimiento\": \"1\", \n        \"Canal\": \"BTDIGITAL\", \n        \"Token\": \"c2cfd09eff4A8B5C60A82434\" \n    }, \n    \"resultado\": \"VERDADERO\", \n    \"retorno\": \"3\", \n    \"Erroresnegocio\": { \n    }, \n    \"Btoutreq\": { \n        \"Numero\": \"44659\", \n        \"Estado\": \"OK\", \n        \"Servicio\": \"BTReglasNegocio.EvaluarReglaNegocio\", \n        \"Fecha\": \"2022-06-02\", \n        \"Requerimiento\": \"1\", \n        \"Hora\": \"10:27:36\", \n        \"Canal\": \"BTDIGITAL\" \n    } \n} \n``` \n</code-block> \n</code-group> \n\n",
    "AzureSearch_DocumentKey": 491
}